gumx/__init__.py
gumx/__main__.py
gumx/consts.py
gumx/setup.py
gumx/utils.py
gumx/functions/__init__.py
gumx/functions/choose.py
gumx/functions/confirm.py
gumx/functions/file.py
gumx/functions/input.py
gumx/functions/pager.py
gumx/functions/search.py
gumx/functions/spin.py
gumx/functions/style.py
gumx/functions/write.py
gumx-0.2.dist-info/LICENSE
gumx-0.2.dist-info/METADATA
gumx-0.2.dist-info/WHEEL
gumx-0.2.dist-info/top_level.txt
gumx-0.2.dist-info/RECORD
