Metadata-Version: 2.2
Name: gumx
Version: 0.2
Summary: Wrapper for GUM
Author-email: Egsagon <egsagon12@gmail.com>
License: MIT License
Project-URL: Repository, https://github.com/Egsagon/gumx
Keywords: gum,cli
Classifier: Development Status :: 5 - Production/Stable
Classifier: Programming Language :: Python
Requires-Python: >=3.11
License-File: LICENSE
Requires-Dist: requests
